Metadata-Version: 1.0
Name: vrt-lss-fieldservice
Version: 3.9.172873
Summary: Veeroute.Fieldservice
Home-page: https://docs.veeroute.com/#/lss/fieldservice
Author: Veeroute Support Team
Author-email: support@veeroute.com
License: UNKNOWN
Keywords: OpenAPI,OpenAPI-Generator,Veeroute.Fieldservice
Platform: UNKNOWN
